lavis/__init__.py
lavis/common/config.py
lavis/common/dist_utils.py
lavis/common/gradcam.py
lavis/common/logger.py
lavis/common/optims.py
lavis/common/registry.py
lavis/common/utils.py
lavis/common/vqa_tools/__init__.py
lavis/common/vqa_tools/vqa.py
lavis/common/vqa_tools/vqa_eval.py
lavis/configs/default.yaml
lavis/configs/datasets/aokvqa/defaults.yaml
lavis/configs/datasets/avsd/defaults_dial.yaml
lavis/configs/datasets/coco/defaults_cap.yaml
lavis/configs/datasets/coco/defaults_ret.yaml
lavis/configs/datasets/coco/defaults_vqa.yaml
lavis/configs/datasets/coco/eval_vqa.yaml
lavis/configs/datasets/conceptual_caption/defaults_12m.yaml
lavis/configs/datasets/conceptual_caption/defaults_3m.yaml
lavis/configs/datasets/didemo/defaults_ret.yaml
lavis/configs/datasets/flickr30k/defaults.yaml
lavis/configs/datasets/gqa/balanced_testdev.yaml
lavis/configs/datasets/gqa/balanced_val.yaml
lavis/configs/datasets/gqa/defaults.yaml
lavis/configs/datasets/imagenet/defaults.yaml
lavis/configs/datasets/laion/defaults_2B_multi.yaml
lavis/configs/datasets/msrvtt/defaults_cap.yaml
lavis/configs/datasets/msrvtt/defaults_qa.yaml
lavis/configs/datasets/msrvtt/defaults_ret.yaml
lavis/configs/datasets/msvd/defaults_cap.yaml
lavis/configs/datasets/msvd/defaults_qa.yaml
lavis/configs/datasets/nlvr/defaults.yaml
lavis/configs/datasets/nocaps/defaults.yaml
lavis/configs/datasets/okvqa/defaults.yaml
lavis/configs/datasets/sbu_caption/defaults.yaml
lavis/configs/datasets/snli_ve/defaults.yaml
lavis/configs/datasets/vatex/defaults_cap.yaml
lavis/configs/datasets/vg/defaults_caption.yaml
lavis/configs/datasets/vg/defaults_vqa.yaml
lavis/configs/models/albef_classification_ve.yaml
lavis/configs/models/albef_feature_extractor.yaml
lavis/configs/models/albef_nlvr.yaml
lavis/configs/models/albef_pretrain_base.yaml
lavis/configs/models/albef_retrieval_coco.yaml
lavis/configs/models/albef_retrieval_flickr.yaml
lavis/configs/models/albef_vqav2.yaml
lavis/configs/models/alpro_qa_msrvtt.yaml
lavis_gml-1.0.2.post5.dist-info/LICENSE.txt
lavis_gml-1.0.2.post5.dist-info/METADATA
lavis_gml-1.0.2.post5.dist-info/WHEEL
lavis_gml-1.0.2.post5.dist-info/top_level.txt
lavis_gml-1.0.2.post5.dist-info/RECORD
