Metadata-Version: 2.1
Name: lavis-gml
Version: 1.0.2.post5
Summary: LAVIS - A One-stop Library for Language-Vision Intelligence
Home-page: https://github.com/gimletlabs/LAVIS
Author: Dongxu Li, Junnan Li, Hung Le, Guangsen Wang, Silvio Savarese, Steven C.H. Hoi
License: 3-Clause BSD
Keywords: Vision-Language,Multimodal,Image Captioning,Generative AI,Deep Learning,Library,PyTorch
Requires-Python: >=3.7.0
License-File: LICENSE.txt
Requires-Dist: decord
Requires-Dist: einops >=0.4.1
Requires-Dist: fairscale ==0.4.4
Requires-Dist: ftfy
Requires-Dist: iopath
Requires-Dist: numpy
Requires-Dist: omegaconf
Requires-Dist: opencv-python-headless
Requires-Dist: opendatasets
Requires-Dist: packaging
Requires-Dist: pandas
Requires-Dist: pycocoevalcap
Requires-Dist: pycocotools
Requires-Dist: python-magic
Requires-Dist: regex
Requires-Dist: requests
Requires-Dist: scikit-image
Requires-Dist: scipy
Requires-Dist: timm ==0.4.12
Requires-Dist: torch >=1.10.0
Requires-Dist: torchvision
Requires-Dist: tqdm
Requires-Dist: transformers
Requires-Dist: webdataset
